LICENSE
MANIFEST.in
README
setup.py
src/watch_rsync/__init__.py
src/watch_rsync/__version__.py
src/watch_rsync/main.py
src/watch_rsync.egg-info/PKG-INFO
src/watch_rsync.egg-info/SOURCES.txt
src/watch_rsync.egg-info/dependency_links.txt
src/watch_rsync.egg-info/entry_points.txt
src/watch_rsync.egg-info/top_level.txt
src/watch_rsync/vendor/argh/__init__.py
src/watch_rsync/vendor/argh/assembling.py
src/watch_rsync/vendor/argh/compat.py
src/watch_rsync/vendor/argh/completion.py
src/watch_rsync/vendor/argh/constants.py
src/watch_rsync/vendor/argh/decorators.py
src/watch_rsync/vendor/argh/dispatching.py
src/watch_rsync/vendor/argh/exceptions.py
src/watch_rsync/vendor/argh/helpers.py
src/watch_rsync/vendor/argh/interaction.py
src/watch_rsync/vendor/argh/io.py
src/watch_rsync/vendor/argh/utils.py
src/watch_rsync/vendor/click/__init__.py
src/watch_rsync/vendor/click/_bashcomplete.py
src/watch_rsync/vendor/click/_compat.py
src/watch_rsync/vendor/click/_termui_impl.py
src/watch_rsync/vendor/click/_textwrap.py
src/watch_rsync/vendor/click/_unicodefun.py
src/watch_rsync/vendor/click/_winconsole.py
src/watch_rsync/vendor/click/core.py
src/watch_rsync/vendor/click/decorators.py
src/watch_rsync/vendor/click/exceptions.py
src/watch_rsync/vendor/click/formatting.py
src/watch_rsync/vendor/click/globals.py
src/watch_rsync/vendor/click/parser.py
src/watch_rsync/vendor/click/termui.py
src/watch_rsync/vendor/click/testing.py
src/watch_rsync/vendor/click/types.py
src/watch_rsync/vendor/click/utils.py
src/watch_rsync/vendor/pathtools/__init__.py
src/watch_rsync/vendor/pathtools/path.py
src/watch_rsync/vendor/pathtools/patterns.py
src/watch_rsync/vendor/pathtools/version.py
src/watch_rsync/vendor/watchdog/__init__.py
src/watch_rsync/vendor/watchdog/events.py
src/watch_rsync/vendor/watchdog/version.py
src/watch_rsync/vendor/watchdog/watchmedo.py
src/watch_rsync/vendor/watchdog/observers/__init__.py
src/watch_rsync/vendor/watchdog/observers/api.py
src/watch_rsync/vendor/watchdog/observers/fsevents.py
src/watch_rsync/vendor/watchdog/observers/fsevents2.py
src/watch_rsync/vendor/watchdog/observers/inotify.py
src/watch_rsync/vendor/watchdog/observers/inotify_buffer.py
